school_scraper/__init__.py
school_scraper/fsddistrict.py
school_scraper/fsdschool.py
school_scraper/fsdscraper.py
school_scraper/version.py
school_scraper-0.0.1.dist-info/LICENSE
school_scraper-0.0.1.dist-info/METADATA
school_scraper-0.0.1.dist-info/WHEEL
school_scraper-0.0.1.dist-info/entry_points.txt
school_scraper-0.0.1.dist-info/top_level.txt
school_scraper-0.0.1.dist-info/RECORD
