Metadata-Version: 2.1
Name: school-scraper
Version: 0.0.1
Summary: Web scraper that parses school closure and late bus announcements from various school websites
Home-page: https://github.com/TheFriendlyCoder/school_scraper
Author: Kevin S. Phillips
Author-email: thefriendlycoder@gmail.com
License: Apache License 2.0
Keywords: web scraper school closure late bus
Platform: UNKNOWN
Classifier: Development Status :: 3 - Alpha
Classifier: Environment :: Console
Classifier: License :: OSI Approved :: Apache Software License
Classifier: Topic :: Software Development :: Libraries
Classifier: Natural Language :: English
Classifier: Operating System :: OS Independent
Classifier: Programming Language :: Python :: 3
Requires-Python: >=3.6.0, <4
Requires-Dist: pandas
Requires-Dist: lxml
Requires-Dist: tabulate
Provides-Extra: dev
Requires-Dist: pytest ; extra == 'dev'
Requires-Dist: pytest-cov ; extra == 'dev'
Requires-Dist: pytest-json-report ; extra == 'dev'
Requires-Dist: mock ; extra == 'dev'
Requires-Dist: pylint ; extra == 'dev'
Requires-Dist: sphinx ; extra == 'dev'
Requires-Dist: sphinxcontrib-apidoc ; extra == 'dev'
Requires-Dist: sphinx-rtd-theme ; extra == 'dev'
Requires-Dist: tox ; extra == 'dev'
Requires-Dist: tox-factor ; extra == 'dev'
Requires-Dist: tox-pyenv ; extra == 'dev'
Requires-Dist: coverage (<5.0) ; extra == 'dev'
Requires-Dist: requests ; extra == 'dev'
